netbox_cisco_support_plugin/__init__.py
netbox_cisco_support_plugin/admin.py
netbox_cisco_support_plugin/filtersets.py
netbox_cisco_support_plugin/forms.py
netbox_cisco_support_plugin/models.py
netbox_cisco_support_plugin/navigation.py
netbox_cisco_support_plugin/tables.py
netbox_cisco_support_plugin/template_content.py
netbox_cisco_support_plugin/urls.py
netbox_cisco_support_plugin/version.py
netbox_cisco_support_plugin/views.py
netbox_cisco_support_plugin/api/__init__.py
netbox_cisco_support_plugin/api/serializers.py
netbox_cisco_support_plugin/api/urls.py
netbox_cisco_support_plugin/api/views.py
netbox_cisco_support_plugin/management/__init__.py
netbox_cisco_support_plugin/management/commands/__init__.py
netbox_cisco_support_plugin/management/commands/sync_cisco_support_data.py
netbox_cisco_support_plugin/migrations/0001_initial.py
netbox_cisco_support_plugin/migrations/0002_ciscodevicesupport_and_more.py
netbox_cisco_support_plugin/migrations/__init__.py
netbox_cisco_support_plugin/templates/netbox_cisco_support_plugin/cisco_support_device.html
netbox_cisco_support_plugin/templates/netbox_cisco_support_plugin/cisco_support_device_type.html
netbox_cisco_support_plugin/templates/netbox_cisco_support_plugin/no_data_available.html
netbox_cisco_support_plugin/templatetags/__init__.py
netbox_cisco_support_plugin/templatetags/filters.py
netbox_cisco_maintenance-0.0.229.dist-info/LICENSE
netbox_cisco_maintenance-0.0.229.dist-info/METADATA
netbox_cisco_maintenance-0.0.229.dist-info/WHEEL
netbox_cisco_maintenance-0.0.229.dist-info/top_level.txt
netbox_cisco_maintenance-0.0.229.dist-info/RECORD
