Metadata-Version: 2.1
Name: netbox-cisco-maintenance
Version: 0.0.229
Summary: Implementing Cisco maintenance information with the Cisco Support APIs into NetBox
Author: Willi Kubny
Author-email: willi.kubny@gmail.com
License: MIT
Classifier: Programming Language :: Python :: 3
Classifier: Framework :: Django
Classifier: Intended Audience :: Information Technology
Classifier: License :: OSI Approved :: MIT License
Classifier: Operating System :: OS Independent
Classifier: Topic :: System :: Networking
Classifier: Topic :: System :: Systems Administration
License-File: LICENSE
